pulsebus/__init__.py
pulsebus/pub_sub_q_event_sys.py
pulsebus/backends/__init__.py
pulsebus/backends/event_driven/__init__.py
pulsebus/backends/event_driven/system_manager.py
pulsebus/backends/event_driven/consumers/__init__.py
pulsebus/backends/event_driven/consumers/base.py
pulsebus/backends/event_driven/consumers/consumers_controller.py
pulsebus/backends/event_driven/core/__init__.py
pulsebus/backends/event_driven/core/exceptions.py
pulsebus/backends/event_driven/core/interfaces.py
pulsebus/backends/event_driven/core/message.py
pulsebus/backends/event_driven/core/message/__init__.py
pulsebus/backends/event_driven/core/message/builder.py
pulsebus/backends/event_driven/core/message/interface.py
pulsebus/backends/event_driven/core/message/message.py
pulsebus/backends/event_driven/core/pool/__init__.py
pulsebus/backends/event_driven/core/pool/message_pool.py
pulsebus/backends/event_driven/producers/__init__.py
pulsebus/backends/event_driven/producers/base.py
pulsebus/backends/event_driven/producers/producers_controller.py
pulsebus/backends/event_driven/queues/Lock_free_queue.py
pulsebus/backends/event_driven/queues/__init__.py
pulsebus/backends/event_driven/queues/base.py
pulsebus/backends/event_driven/utils/__init__.py
pulsebus/backends/event_driven/utils/config.py
pulsebus/backends/event_driven/utils/serializers.py
pulsebus-2.0.7.dist-info/METADATA
pulsebus-2.0.7.dist-info/WHEEL
pulsebus-2.0.7.dist-info/top_level.txt
pulsebus-2.0.7.dist-info/RECORD
