Metadata-Version: 2.4
Name: pulsebus
Version: 2.0.7
Summary: General-purpose message routing framework built upon an event driven architecture, handles up to very large amounts of data transmition and channeling with concurrent consumers and producers.
Author-email: Your Name <your@email.com>
License: MIT
